shearer/__init__.py
shearer/configs/__init__.py
shearer/configs/llm.py
shearer/models.py
shearer/prompts/__init__.py
shearer/prompts/xml/__init__.py
shearer/prompts/xml/prompt.py
shearer/scraper/__init__.py
shearer/scraper/base.py
shearer/scraper/xml.py
shearer/utils/__init__.py
shearer/utils/token.py
shearer-0.1.1.dist-info/METADATA
shearer-0.1.1.dist-info/WHEEL
shearer-0.1.1.dist-info/RECORD
